aleksis/apps/buelleten/__init__.py
aleksis/apps/buelleten/apps.py
aleksis/apps/buelleten/filters.py
aleksis/apps/buelleten/forms.py
aleksis/apps/buelleten/frontend/index.js
aleksis/apps/buelleten/frontend/messages/de.json
aleksis/apps/buelleten/frontend/messages/en.json
aleksis/apps/buelleten/locale/.keepdir
aleksis/apps/buelleten/locale/ar/LC_MESSAGES/django.mo
aleksis/apps/buelleten/locale/ar/LC_MESSAGES/django.po
aleksis/apps/buelleten/locale/de_DE/LC_MESSAGES/django.mo
aleksis/apps/buelleten/locale/de_DE/LC_MESSAGES/django.po
aleksis/apps/buelleten/locale/fr/LC_MESSAGES/django.mo
aleksis/apps/buelleten/locale/fr/LC_MESSAGES/django.po
aleksis/apps/buelleten/locale/la/LC_MESSAGES/django.mo
aleksis/apps/buelleten/locale/la/LC_MESSAGES/django.po
aleksis/apps/buelleten/locale/nb_NO/LC_MESSAGES/django.mo
aleksis/apps/buelleten/locale/nb_NO/LC_MESSAGES/django.po
aleksis/apps/buelleten/locale/ru/LC_MESSAGES/django.mo
aleksis/apps/buelleten/locale/ru/LC_MESSAGES/django.po
aleksis/apps/buelleten/locale/tr_TR/LC_MESSAGES/django.mo
aleksis/apps/buelleten/locale/tr_TR/LC_MESSAGES/django.po
aleksis/apps/buelleten/locale/uk/LC_MESSAGES/django.mo
aleksis/apps/buelleten/locale/uk/LC_MESSAGES/django.po
aleksis/apps/buelleten/migrations/0001_initial.py
aleksis/apps/buelleten/migrations/0002_display_variants.py
aleksis/apps/buelleten/migrations/0003_verbose_names_site_related_name_description_blank.py
aleksis/apps/buelleten/migrations/0004_add_managed_by_app_label.py
aleksis/apps/buelleten/migrations/0005_alter_display_managers_alter_displaygroup_managers.py
aleksis/apps/buelleten/migrations/__init__.py
aleksis/apps/buelleten/models/__init__.py
aleksis/apps/buelleten/models/base.py
aleksis/apps/buelleten/models/slides.py
aleksis/apps/buelleten/rules.py
aleksis/apps/buelleten/static/.keepdir
aleksis/apps/buelleten/tables.py
aleksis/apps/buelleten/templates/buelleten/display/create.html
aleksis/apps/buelleten/templates/buelleten/display/edit.html
aleksis_app_buelleten-3.0.0.dev1.dist-info/METADATA
aleksis_app_buelleten-3.0.0.dev1.dist-info/WHEEL
aleksis_app_buelleten-3.0.0.dev1.dist-info/entry_points.txt
aleksis_app_buelleten-3.0.0.dev1.dist-info/RECORD
