Metadata-Version: 2.1
Name: AlekSIS-App-Buelleten
Version: 3.0.0.dev1
Summary: AlekSIS (School Information System) — App Bülleten (Digital Signage)
Home-page: https://aleksis.org
License: EUPL-1.2-or-later
Author: Tom Teichler
Author-email: tom.teichler@teckids.org
Maintainer: Jonathan Weth
Maintainer-email: dev@jonathanweth.de
Requires-Python: >=3.10,<4.0
Classifier: Environment :: Web Environment
Classifier: Intended Audience :: Education
Classifier: License :: Other/Proprietary License
Classifier: Programming Language :: Python :: 3
Classifier: Programming Language :: Python :: 3.10
Classifier: Programming Language :: Python :: 3.11
Classifier: Topic :: Education
Requires-Dist: aleksis-core (>=4.0.0.dev2,<5.0.0)
Project-URL: Documentation, https://aleksis.edugit.io/official/AlekSIS-Core/docs/html/
Project-URL: Repository, https://edugit.org/AlekSIS/onboarding//AlekSIS-App-Buelleten
